{"_ts":[1561949560,1561993721],"_r":{"breakdown":{"html":{"bytes":[28392,28392],"requests":[1,1]},"js":{"bytes":[309260,309259],"requests":[15,15]},"css":{"bytes":[106530,106530],"requests":[4,4]},"image":{"bytes":[261604,261604],"requests":[21,21]},"flash":{"bytes":[0,0],"requests":[0,0]},"font":{"bytes":[112284,112284],"requests":[3,3]},"video":{"bytes":[0,0],"requests":[0,0]},"other":{"bytes":[0,0],"requests":[0,0]}},"date":[1561949560,1561993721],"domElements":[1141,1141],"domInteractive":[10660,16914],"firstPaint":[10390.5099999974,16778.3649999983],"fullyLoaded":[11652,18110],"id":["190701_ZH_a51523a45e11682443b7074162240560","190701_YP_d4ffe01e91db86861903a3de99b263eb"],"loadTime":[11552,18001],"render":[10400,16800],"SpeedIndex":[11038,17522],"TTFB":[9285,15665],"videoFrames":[[{"_i":"ms_000000.jpg","_t":0,"_vc":0},{"_i":"ms_010400.jpg","_t":10400,"_vc":0},{"_i":"ms_010500.jpg","_t":10500,"_vc":9},{"_i":"ms_010600.jpg","_t":10600,"_vc":12},{"_i":"ms_010700.jpg","_t":10700,"_vc":12},{"_i":"ms_011100.jpg","_t":11100,"_vc":93},{"_i":"ms_011200.jpg","_t":11200,"_vc":100}],[{"_i":"ms_000000.jpg","_t":0,"_vc":0},{"_i":"ms_016800.jpg","_t":16800,"_vc":7},{"_i":"ms_016900.jpg","_t":16900,"_vc":9},{"_i":"ms_017400.jpg","_t":17400,"_vc":13},{"_i":"ms_017600.jpg","_t":17600,"_vc":100}]],"visualComplete":[11200,17600],"lighthouse":[57,57],"pagespeed":[58,44]}}