{"_ts":[1519874181,1519918843],"_r":{"breakdown":{"html":{"bytes":[36166,36104],"requests":[27,28]},"js":{"bytes":[200982,201163],"requests":[27,27]},"css":{"bytes":[33007,33030],"requests":[6,6]},"image":{"bytes":[492244,492769],"requests":[44,45]},"flash":{"bytes":[0,0],"requests":[0,0]},"font":{"bytes":[135101,135170],"requests":[6,6]},"video":{"bytes":[0,0],"requests":[0,0]},"other":{"bytes":[2819,2796],"requests":[27,27]}},"date":[1519874181,1519918843],"domElements":[846,846],"domInteractive":[5605,7593],"firstPaint":[5297.5999999999,7279.7999999966],"fullyLoaded":[8282,12406],"id":["180301_FQ_593815ca4af2d6a1cb8ad9600113a8c9","180301_K2_bf3c699b1ef849a1cdd3401d27550cdf"],"loadTime":[6935,9340],"render":[5700,7500],"SpeedIndex":[6803,8707],"TTFB":[4557,6666],"videoFrames":[[{"_i":"ms_000000.jpg","_t":0,"_vc":0},{"_i":"ms_005700.jpg","_t":5700,"_vc":9},{"_i":"ms_006100.jpg","_t":6100,"_vc":9},{"_i":"ms_006200.jpg","_t":6200,"_vc":9},{"_i":"ms_006800.jpg","_t":6800,"_vc":8},{"_i":"ms_006900.jpg","_t":6900,"_vc":98},{"_i":"ms_007100.jpg","_t":7100,"_vc":99},{"_i":"ms_007500.jpg","_t":7500,"_vc":99},{"_i":"ms_007600.jpg","_t":7600,"_vc":99},{"_i":"ms_007700.jpg","_t":7700,"_vc":100}],[{"_i":"ms_000000.jpg","_t":0,"_vc":0},{"_i":"ms_007500.jpg","_t":7500,"_vc":8},{"_i":"ms_008000.jpg","_t":8000,"_vc":8},{"_i":"ms_008100.jpg","_t":8100,"_vc":9},{"_i":"ms_008200.jpg","_t":8200,"_vc":8},{"_i":"ms_008700.jpg","_t":8700,"_vc":8},{"_i":"ms_008800.jpg","_t":8800,"_vc":98},{"_i":"ms_009000.jpg","_t":9000,"_vc":99},{"_i":"ms_009600.jpg","_t":9600,"_vc":99},{"_i":"ms_009700.jpg","_t":9700,"_vc":99},{"_i":"ms_009800.jpg","_t":9800,"_vc":100}]],"visualComplete":[7700,9800],"lighthouse":[36,36],"pagespeed":[68,68]}}