{"_ts":[1538376149],"_r":{"breakdown":{"html":{"bytes":[34746],"requests":[26]},"js":{"bytes":[224642],"requests":[29]},"css":{"bytes":[33122],"requests":[6]},"image":{"bytes":[654030],"requests":[48]},"flash":{"bytes":[0],"requests":[0]},"font":{"bytes":[135228],"requests":[6]},"video":{"bytes":[0],"requests":[0]},"other":{"bytes":[2912],"requests":[27]}},"date":[1538376149],"domElements":[881],"domInteractive":[6221],"firstPaint":[6218.200000003],"fullyLoaded":[9725],"id":["181001_F0_45dbe1144dd13aa09541fb9f3e0397f5"],"loadTime":[8110],"render":[6200],"SpeedIndex":[7586],"TTFB":[4942],"videoFrames":[[{"_i":"ms_000000.jpg","_t":0,"_vc":0},{"_i":"ms_006200.jpg","_t":6200,"_vc":7},{"_i":"ms_006800.jpg","_t":6800,"_vc":8},{"_i":"ms_006900.jpg","_t":6900,"_vc":8},{"_i":"ms_007200.jpg","_t":7200,"_vc":8},{"_i":"ms_007500.jpg","_t":7500,"_vc":8},{"_i":"ms_007700.jpg","_t":7700,"_vc":100}]],"visualComplete":[7700],"lighthouse":[15],"pagespeed":[63]}}