{"_ts":[1575163208,1575207134,1575296046],"_r":{"breakdown":{"html":{"bytes":[1236,1236,23759],"requests":[1,1,3]},"js":{"bytes":[0,0,114505],"requests":[0,0,23]},"css":{"bytes":[0,0,31533],"requests":[0,0,6]},"image":{"bytes":[0,0,250543],"requests":[0,0,6]},"flash":{"bytes":[0,0,0],"requests":[0,0,0]},"font":{"bytes":[0,0,133836],"requests":[0,0,6]},"video":{"bytes":[0,0,0],"requests":[0,0,0]},"other":{"bytes":[0,0,205],"requests":[0,0,2]}},"date":[1575163208,1575207134,1575296046],"domElements":[null,null,565],"domInteractive":[null,null,78948],"firstPaint":[null,null,78806.5349999961],"fullyLoaded":[null,null,83448],"id":["191201_FK_11a8cba17011680538648d48b183cb5f","191201_JK_cfcc8aa550bbffb1d6720f855611f391","191202_PF_afca561c9f2911049e145a711686ce5d"],"loadTime":[null,null,83328],"render":[null,null,78800],"SpeedIndex":[null,null,83043],"TTFB":[null,null,77954],"videoFrames":[[{"_i":"ms_000000.jpg","_t":0,"_vc":100}],[{"_i":"ms_000000.jpg","_t":0,"_vc":100}],[{"_i":"ms_000000.jpg","_t":0,"_vc":0},{"_i":"ms_078800.jpg","_t":78800,"_vc":3},{"_i":"ms_078900.jpg","_t":78900,"_vc":3},{"_i":"ms_079000.jpg","_t":79000,"_vc":8},{"_i":"ms_079400.jpg","_t":79400,"_vc":8},{"_i":"ms_079500.jpg","_t":79500,"_vc":8},{"_i":"ms_079600.jpg","_t":79600,"_vc":7},{"_i":"ms_079700.jpg","_t":79700,"_vc":8},{"_i":"ms_083200.jpg","_t":83200,"_vc":8},{"_i":"ms_083400.jpg","_t":83400,"_vc":100}]],"visualComplete":[null,null,83400],"lighthouse":[null,null,null],"pagespeed":[100,100,null]}}