{"_ts":[1543637943],"_r":{"breakdown":{"html":{"bytes":[23199],"requests":[1]},"js":{"bytes":[358791],"requests":[16]},"css":{"bytes":[107719],"requests":[4]},"image":{"bytes":[394726],"requests":[16]},"flash":{"bytes":[0],"requests":[0]},"font":{"bytes":[133996],"requests":[4]},"video":{"bytes":[0],"requests":[0]},"other":{"bytes":[0],"requests":[0]}},"date":[1543637943],"domElements":[1013],"domInteractive":[49403],"firstPaint":[49292.399999999],"fullyLoaded":[52575],"id":["181201_S8_80cbb6fe033c31e07d530a298bb14c72"],"loadTime":[51770],"render":[49300],"SpeedIndex":[51142],"TTFB":[28947],"videoFrames":[[{"_i":"ms_000000.jpg","_t":0,"_vc":0},{"_i":"ms_049300.jpg","_t":49300,"_vc":3},{"_i":"ms_049400.jpg","_t":49400,"_vc":6},{"_i":"ms_049600.jpg","_t":49600,"_vc":11},{"_i":"ms_050100.jpg","_t":50100,"_vc":11},{"_i":"ms_050600.jpg","_t":50600,"_vc":12},{"_i":"ms_050700.jpg","_t":50700,"_vc":12},{"_i":"ms_051000.jpg","_t":51000,"_vc":19},{"_i":"ms_051100.jpg","_t":51100,"_vc":20},{"_i":"ms_051200.jpg","_t":51200,"_vc":78},{"_i":"ms_051900.jpg","_t":51900,"_vc":100}]],"visualComplete":[51900],"lighthouse":[57],"pagespeed":[62]}}