{"_ts":[1567342050],"_r":{"breakdown":{"html":{"bytes":[74889],"requests":[4]},"js":{"bytes":[922555],"requests":[29]},"css":{"bytes":[162492],"requests":[6]},"image":{"bytes":[626750],"requests":[37]},"flash":{"bytes":[0],"requests":[0]},"font":{"bytes":[179568],"requests":[7]},"video":{"bytes":[0],"requests":[0]},"other":{"bytes":[344],"requests":[2]}},"date":[1567342050],"domElements":[1285],"domInteractive":[5071],"firstPaint":[3622.3800000007],"fullyLoaded":[8841],"id":["190901_KX_1b0eba54a0db3492de7c7fecfc3b7384"],"loadTime":[7018],"render":[3700],"SpeedIndex":[4731],"TTFB":[2655],"videoFrames":[[{"_i":"ms_000000.jpg","_t":0,"_vc":0},{"_i":"ms_003700.jpg","_t":3700,"_vc":4},{"_i":"ms_003800.jpg","_t":3800,"_vc":7},{"_i":"ms_004300.jpg","_t":4300,"_vc":7},{"_i":"ms_004400.jpg","_t":4400,"_vc":6},{"_i":"ms_004500.jpg","_t":4500,"_vc":6},{"_i":"ms_004600.jpg","_t":4600,"_vc":9},{"_i":"ms_004800.jpg","_t":4800,"_vc":99},{"_i":"ms_004900.jpg","_t":4900,"_vc":99},{"_i":"ms_005000.jpg","_t":5000,"_vc":99},{"_i":"ms_005500.jpg","_t":5500,"_vc":100}]],"visualComplete":[5500],"lighthouse":[31],"pagespeed":[59]}}