{"_ts":[1530422911],"_r":{"breakdown":{"html":{"bytes":[35455],"requests":[1]},"js":{"bytes":[250760],"requests":[10]},"css":{"bytes":[105307],"requests":[4]},"image":{"bytes":[235922],"requests":[31]},"flash":{"bytes":[0],"requests":[0]},"font":{"bytes":[133788],"requests":[4]},"video":{"bytes":[0],"requests":[0]},"other":{"bytes":[0],"requests":[0]}},"date":[1530422911],"domElements":[1526],"domInteractive":[4761],"firstPaint":[4407.9999999958],"fullyLoaded":[7060],"id":["180701_V2_d20d9f6a5b9f92142bef1b3d12c8a479"],"loadTime":[5301],"render":[4500],"SpeedIndex":[5099],"TTFB":[3512],"videoFrames":[[{"_i":"ms_000000.jpg","_t":0,"_vc":0},{"_i":"ms_004500.jpg","_t":4500,"_vc":14},{"_i":"ms_004600.jpg","_t":4600,"_vc":19},{"_i":"ms_004700.jpg","_t":4700,"_vc":28},{"_i":"ms_004800.jpg","_t":4800,"_vc":28},{"_i":"ms_005200.jpg","_t":5200,"_vc":28},{"_i":"ms_005300.jpg","_t":5300,"_vc":100}]],"visualComplete":[5300],"lighthouse":[57],"pagespeed":[70]}}