{"_ts":[1543643294],"_r":{"breakdown":{"html":{"bytes":[36055],"requests":[1]},"js":{"bytes":[279384],"requests":[11]},"css":{"bytes":[107719],"requests":[4]},"image":{"bytes":[241283],"requests":[36]},"flash":{"bytes":[0],"requests":[0]},"font":{"bytes":[133996],"requests":[4]},"video":{"bytes":[0],"requests":[0]},"other":{"bytes":[0],"requests":[0]}},"date":[1543643294],"domElements":[1567],"domInteractive":[4261],"firstPaint":[4051.1000000006],"fullyLoaded":[5679],"id":["181201_3J_541f2d30424665f1884d3b2cf5a3581f"],"loadTime":[4921],"render":[4100],"SpeedIndex":[4736],"TTFB":[2901],"videoFrames":[[{"_i":"ms_000000.jpg","_t":0,"_vc":0},{"_i":"ms_004100.jpg","_t":4100,"_vc":11},{"_i":"ms_004300.jpg","_t":4300,"_vc":23},{"_i":"ms_004500.jpg","_t":4500,"_vc":24},{"_i":"ms_004900.jpg","_t":4900,"_vc":100}]],"visualComplete":[4900],"lighthouse":[57],"pagespeed":[65]}}