{"_ts":[1522556395,1522688078,1522775706,1522819801],"_r":{"breakdown":{"html":{"bytes":[39002,39004,39002,39002],"requests":[23,22,23,23]},"js":{"bytes":[1016102,1016335,1016342,1017041],"requests":[46,46,46,46]},"css":{"bytes":[120843,120843,120843,120843],"requests":[5,5,5,5]},"image":{"bytes":[311767,310601,311588,311649],"requests":[61,56,60,61]},"flash":{"bytes":[0,0,0,0],"requests":[0,0,0,0]},"font":{"bytes":[149657,149657,149657,149656],"requests":[5,5,5,5]},"video":{"bytes":[0,0,0,0],"requests":[0,0,0,0]},"other":{"bytes":[10980,10581,10602,10598],"requests":[26,24,24,24]}},"date":[1522556395,1522688078,1522775706,1522819801],"domElements":[1375,1375,1375,1376],"domInteractive":[11058,7508,7004,32747],"firstPaint":[8865.2999999977,5526.7000000022,4816.5000000008,30395.799999998],"fullyLoaded":[14562,13210,10508,36972],"id":["180401_40_2461e30af3b2313ee0d8cbdb37736089","180402_4G_4015f93bab2ab5f9e403f9720d305c32","180403_GS_a4f688c15b45eb502fe02886a9e7fea8","180404_4K_c3bdbcd77f5362dd2552f3b790af2298"],"loadTime":[12909,11469,8907,35323],"render":[9000,5600,4800,30600],"SpeedIndex":[10450,6856,6324,31832],"TTFB":[7768,4494,3835,12402],"videoFrames":[[{"_i":"ms_000000.jpg","_t":0,"_vc":0},{"_i":"ms_009000.jpg","_t":9000,"_vc":2},{"_i":"ms_009100.jpg","_t":9100,"_vc":9},{"_i":"ms_010500.jpg","_t":10500,"_vc":25},{"_i":"ms_010600.jpg","_t":10600,"_vc":100},{"_i":"ms_010900.jpg","_t":10900,"_vc":100},{"_i":"ms_011100.jpg","_t":11100,"_vc":100},{"_i":"ms_011200.jpg","_t":11200,"_vc":100},{"_i":"ms_011400.jpg","_t":11400,"_vc":100},{"_i":"ms_011900.jpg","_t":11900,"_vc":100},{"_i":"ms_012200.jpg","_t":12200,"_vc":100},{"_i":"ms_012700.jpg","_t":12700,"_vc":100},{"_i":"ms_012800.jpg","_t":12800,"_vc":100},{"_i":"ms_012900.jpg","_t":12900,"_vc":99},{"_i":"ms_013200.jpg","_t":13200,"_vc":100},{"_i":"ms_013700.jpg","_t":13700,"_vc":100},{"_i":"ms_013800.jpg","_t":13800,"_vc":100}],[{"_i":"ms_000000.jpg","_t":0,"_vc":0},{"_i":"ms_005600.jpg","_t":5600,"_vc":11},{"_i":"ms_005700.jpg","_t":5700,"_vc":11},{"_i":"ms_006200.jpg","_t":6200,"_vc":11},{"_i":"ms_006300.jpg","_t":6300,"_vc":10},{"_i":"ms_006400.jpg","_t":6400,"_vc":10},{"_i":"ms_006900.jpg","_t":6900,"_vc":11},{"_i":"ms_007000.jpg","_t":7000,"_vc":100},{"_i":"ms_007200.jpg","_t":7200,"_vc":100},{"_i":"ms_007500.jpg","_t":7500,"_vc":100},{"_i":"ms_007600.jpg","_t":7600,"_vc":100},{"_i":"ms_007700.jpg","_t":7700,"_vc":100},{"_i":"ms_007800.jpg","_t":7800,"_vc":100},{"_i":"ms_008300.jpg","_t":8300,"_vc":100},{"_i":"ms_008500.jpg","_t":8500,"_vc":100},{"_i":"ms_009100.jpg","_t":9100,"_vc":100},{"_i":"ms_009200.jpg","_t":9200,"_vc":99},{"_i":"ms_009300.jpg","_t":9300,"_vc":99},{"_i":"ms_009600.jpg","_t":9600,"_vc":100},{"_i":"ms_009800.jpg","_t":9800,"_vc":100},{"_i":"ms_010000.jpg","_t":10000,"_vc":100},{"_i":"ms_010300.jpg","_t":10300,"_vc":100},{"_i":"ms_010500.jpg","_t":10500,"_vc":100},{"_i":"ms_010800.jpg","_t":10800,"_vc":100},{"_i":"ms_012100.jpg","_t":12100,"_vc":100}],[{"_i":"ms_000000.jpg","_t":0,"_vc":0},{"_i":"ms_004800.jpg","_t":4800,"_vc":2},{"_i":"ms_004900.jpg","_t":4900,"_vc":9},{"_i":"ms_005000.jpg","_t":5000,"_vc":10},{"_i":"ms_006200.jpg","_t":6200,"_vc":11},{"_i":"ms_006400.jpg","_t":6400,"_vc":26},{"_i":"ms_006500.jpg","_t":6500,"_vc":100},{"_i":"ms_006700.jpg","_t":6700,"_vc":100},{"_i":"ms_007000.jpg","_t":7000,"_vc":100},{"_i":"ms_007100.jpg","_t":7100,"_vc":100},{"_i":"ms_007300.jpg","_t":7300,"_vc":100},{"_i":"ms_007900.jpg","_t":7900,"_vc":100},{"_i":"ms_008200.jpg","_t":8200,"_vc":100},{"_i":"ms_008700.jpg","_t":8700,"_vc":100},{"_i":"ms_008800.jpg","_t":8800,"_vc":100},{"_i":"ms_008900.jpg","_t":8900,"_vc":99},{"_i":"ms_009200.jpg","_t":9200,"_vc":100},{"_i":"ms_009700.jpg","_t":9700,"_vc":100}],[{"_i":"ms_000000.jpg","_t":0,"_vc":0},{"_i":"ms_030600.jpg","_t":30600,"_vc":6},{"_i":"ms_031600.jpg","_t":31600,"_vc":6},{"_i":"ms_031901.jpg","_t":31901,"_vc":99},{"_i":"ms_032100.jpg","_t":32100,"_vc":99},{"_i":"ms_032200.jpg","_t":32200,"_vc":97},{"_i":"ms_032300.jpg","_t":32300,"_vc":99},{"_i":"ms_032400.jpg","_t":32400,"_vc":99},{"_i":"ms_032600.jpg","_t":32600,"_vc":99},{"_i":"ms_032700.jpg","_t":32700,"_vc":100},{"_i":"ms_032800.jpg","_t":32800,"_vc":100},{"_i":"ms_033000.jpg","_t":33000,"_vc":100},{"_i":"ms_033400.jpg","_t":33400,"_vc":100},{"_i":"ms_033500.jpg","_t":33500,"_vc":100},{"_i":"ms_033700.jpg","_t":33700,"_vc":100},{"_i":"ms_033900.jpg","_t":33900,"_vc":100},{"_i":"ms_034100.jpg","_t":34100,"_vc":100},{"_i":"ms_034700.jpg","_t":34700,"_vc":100},{"_i":"ms_034800.jpg","_t":34800,"_vc":100},{"_i":"ms_035400.jpg","_t":35400,"_vc":100},{"_i":"ms_035700.jpg","_t":35700,"_vc":100},{"_i":"ms_036200.jpg","_t":36200,"_vc":100},{"_i":"ms_036300.jpg","_t":36300,"_vc":100}]],"visualComplete":[10600,7000,6500,32700],"lighthouse":[54,54,54,54],"pagespeed":[55,54,55,54]}}