{"_ts":[1546317902],"_r":{"breakdown":{"html":{"bytes":[32530],"requests":[31]},"js":{"bytes":[232031],"requests":[29]},"css":{"bytes":[33122],"requests":[6]},"image":{"bytes":[662005],"requests":[46]},"flash":{"bytes":[0],"requests":[0]},"font":{"bytes":[135228],"requests":[6]},"video":{"bytes":[0],"requests":[0]},"other":{"bytes":[2435],"requests":[6]}},"date":[1546317902],"domElements":[896],"domInteractive":[3874],"firstPaint":[3908.7],"fullyLoaded":[8785],"id":["190101_1Z_119d5ae040ee554c683d9e3a7dba205c"],"loadTime":[5771],"render":[3900],"SpeedIndex":[5648],"TTFB":[2725],"videoFrames":[[{"_i":"ms_000000.jpg","_t":0,"_vc":0},{"_i":"ms_003900.jpg","_t":3900,"_vc":8},{"_i":"ms_005000.jpg","_t":5000,"_vc":8},{"_i":"ms_005600.jpg","_t":5600,"_vc":8},{"_i":"ms_005800.jpg","_t":5800,"_vc":100}]],"visualComplete":[5800],"lighthouse":[15],"pagespeed":[63]}}