{"_ts":[1548990970,1549035863],"_r":{"breakdown":{"html":{"bytes":[0,32399],"requests":[0,2]},"js":{"bytes":[0,277205],"requests":[0,11]},"css":{"bytes":[0,106530],"requests":[0,4]},"image":{"bytes":[0,99016],"requests":[0,32]},"flash":{"bytes":[0,0],"requests":[0,0]},"font":{"bytes":[0,132936],"requests":[0,4]},"video":{"bytes":[0,0],"requests":[0,0]},"other":{"bytes":[0,0],"requests":[0,0]}},"date":[1548990970,1549035863],"domElements":[null,1336],"domInteractive":[null,6041],"firstPaint":[null,5830.1600000013],"fullyLoaded":[null,7609],"id":["190201_P6_cda397ca2fc40c2e2ee38dbba44abf2a","190201_01_a111c83d33591d4cf6f589d82f77daea"],"loadTime":[null,6465],"render":[null,5900],"SpeedIndex":[null,6090],"TTFB":[null,3294],"videoFrames":[[{"_i":"ms_000000.jpg","_t":0,"_vc":100}],[{"_i":"ms_000000.jpg","_t":0,"_vc":0},{"_i":"ms_005900.jpg","_t":5900,"_vc":45},{"_i":"ms_006000.jpg","_t":6000,"_vc":50},{"_i":"ms_006100.jpg","_t":6100,"_vc":58},{"_i":"ms_006300.jpg","_t":6300,"_vc":99},{"_i":"ms_006400.jpg","_t":6400,"_vc":100}]],"visualComplete":[null,6400],"lighthouse":[null,57],"pagespeed":[null,67]}}