{"_ts":[1559440094],"_r":{"breakdown":{"html":{"bytes":[35018],"requests":[2]},"js":{"bytes":[309109],"requests":[15]},"css":{"bytes":[106530],"requests":[4]},"image":{"bytes":[154392],"requests":[31]},"flash":{"bytes":[0],"requests":[0]},"font":{"bytes":[132936],"requests":[4]},"video":{"bytes":[0],"requests":[0]},"other":{"bytes":[0],"requests":[0]}},"date":[1559440094],"domElements":[1346],"domInteractive":[4608],"firstPaint":[4037.3199999885],"fullyLoaded":[5453],"id":["190602_X8_65968dc1a4da2629d1daf584bc8f5e7a"],"loadTime":[5357],"render":[4000],"SpeedIndex":[4167],"TTFB":[2959],"videoFrames":[[{"_i":"ms_000000.jpg","_t":0,"_vc":0},{"_i":"ms_004000.jpg","_t":4000,"_vc":40},{"_i":"ms_004100.jpg","_t":4100,"_vc":44},{"_i":"ms_004200.jpg","_t":4200,"_vc":51},{"_i":"ms_004300.jpg","_t":4300,"_vc":98},{"_i":"ms_004400.jpg","_t":4400,"_vc":100}]],"visualComplete":[4400],"lighthouse":[57],"pagespeed":[65]}}