{"_ts":[1519981971],"_r":{"breakdown":{"html":{"bytes":[20494],"requests":[3]},"js":{"bytes":[118471],"requests":[23]},"css":{"bytes":[33471],"requests":[7]},"image":{"bytes":[396478],"requests":[4]},"flash":{"bytes":[0],"requests":[0]},"font":{"bytes":[161694],"requests":[7]},"video":{"bytes":[0],"requests":[0]},"other":{"bytes":[0],"requests":[0]}},"date":[1519981971],"domElements":[713],"domInteractive":[7284],"firstPaint":[7329.9000000006],"fullyLoaded":[11280],"id":["180302_C3_280d88a9c99265f81f2b98ae402c9ce7"],"loadTime":[8408],"render":[7400],"SpeedIndex":[8482],"TTFB":[5599],"videoFrames":[[{"_i":"ms_000000.jpg","_t":0,"_vc":0},{"_i":"ms_007400.jpg","_t":7400,"_vc":6},{"_i":"ms_007500.jpg","_t":7500,"_vc":6},{"_i":"ms_007800.jpg","_t":7800,"_vc":6},{"_i":"ms_008300.jpg","_t":8300,"_vc":6},{"_i":"ms_008400.jpg","_t":8400,"_vc":7},{"_i":"ms_008500.jpg","_t":8500,"_vc":51},{"_i":"ms_008600.jpg","_t":8600,"_vc":100},{"_i":"ms_008700.jpg","_t":8700,"_vc":100}]],"visualComplete":[8600],"lighthouse":[54],"pagespeed":[63]}}