{"_ts":[1512125837,1512169593],"_r":{"breakdown":{"html":{"bytes":[36451,36453],"requests":[22,22]},"js":{"bytes":[956636,1326468],"requests":[18,37]},"css":{"bytes":[87457,87433],"requests":[2,2]},"image":{"bytes":[346179,345420],"requests":[42,41]},"flash":{"bytes":[0,0],"requests":[0,0]},"font":{"bytes":[112977,112977],"requests":[3,3]},"video":{"bytes":[0,0],"requests":[0,0]},"other":{"bytes":[14831,10092],"requests":[5,4]}},"date":[1512125837,1512169593],"domElements":[1128,1151],"domInteractive":[10965,23299],"firstPaint":[9157,19427],"fullyLoaded":[18074,29414],"id":["171201_CE_5a49ffa2c4e1a4a8b105fff1fa14999e","171201_P2_31bc470caba8ad9b081731e36a8f0ca0"],"loadTime":[12296,25866],"render":[9291,19490],"SpeedIndex":[10098,24255],"TTFB":[8456,12880],"videoFrames":[[{"_i":"frame_0000.jpg","_t":0,"_vc":0},{"_i":"frame_0093.jpg","_t":9300,"_vc":0},{"_i":"frame_0097.jpg","_t":9700,"_vc":0},{"_i":"frame_0099.jpg","_t":9900,"_vc":1},{"_i":"frame_0101.jpg","_t":10100,"_vc":100}],[{"_i":"frame_0000.jpg","_t":0,"_vc":0},{"_i":"frame_0195.jpg","_t":19500,"_vc":0},{"_i":"frame_0200.jpg","_t":20000,"_vc":0},{"_i":"frame_0216.jpg","_t":21600,"_vc":1},{"_i":"frame_0232.jpg","_t":23200,"_vc":1},{"_i":"frame_0234.jpg","_t":23400,"_vc":3},{"_i":"frame_0243.jpg","_t":24300,"_vc":100}]],"visualComplete":[10100,24300],"lighthouse":[null,null],"pagespeed":[47,54]}}