{"_ts":[1533105514,1533149628],"_r":{"breakdown":{"html":{"bytes":[32125,32125],"requests":[1,1]},"js":{"bytes":[398504,400552],"requests":[18,20]},"css":{"bytes":[106380,106380],"requests":[5,5]},"image":{"bytes":[333438,333461],"requests":[29,29]},"flash":{"bytes":[0,0],"requests":[0,0]},"font":{"bytes":[149476,149475],"requests":[5,5]},"video":{"bytes":[0,0],"requests":[0,0]},"other":{"bytes":[952,952],"requests":[1,1]}},"date":[1533105514,1533149628],"domElements":[1309,1309],"domInteractive":[6239,5080],"firstPaint":[4490.0999999954,3774.6999999999],"fullyLoaded":[7002,9002],"id":["180801_72_bbb54c321a436d964917d3fa50752b31","180801_B8_cefa43d388c408e71f5c02c79fb3b401"],"loadTime":[6623,5544],"render":[4500,3900],"SpeedIndex":[5818,4781],"TTFB":[3492,2589],"videoFrames":[[{"_i":"ms_000000.jpg","_t":0,"_vc":0},{"_i":"ms_004500.jpg","_t":4500,"_vc":6},{"_i":"ms_005700.jpg","_t":5700,"_vc":6},{"_i":"ms_005800.jpg","_t":5800,"_vc":6},{"_i":"ms_005900.jpg","_t":5900,"_vc":99},{"_i":"ms_006000.jpg","_t":6000,"_vc":99},{"_i":"ms_006100.jpg","_t":6100,"_vc":100},{"_i":"ms_006200.jpg","_t":6200,"_vc":100},{"_i":"ms_006300.jpg","_t":6300,"_vc":100}],[{"_i":"ms_000000.jpg","_t":0,"_vc":0},{"_i":"ms_003900.jpg","_t":3900,"_vc":6},{"_i":"ms_004400.jpg","_t":4400,"_vc":6},{"_i":"ms_004600.jpg","_t":4600,"_vc":26},{"_i":"ms_004700.jpg","_t":4700,"_vc":26},{"_i":"ms_004800.jpg","_t":4800,"_vc":26},{"_i":"ms_004900.jpg","_t":4900,"_vc":99},{"_i":"ms_005000.jpg","_t":5000,"_vc":100},{"_i":"ms_005400.jpg","_t":5400,"_vc":100},{"_i":"ms_005600.jpg","_t":5600,"_vc":100}]],"visualComplete":[6100,5000],"lighthouse":[31,57],"pagespeed":[60,62]}}